{
    "users": [
        {
            "id": 1,
            "name": "User 1",
            "scores": {
                "week": 75,
                "month": 85,
                "allTime": 90
            }
        },
        {
            "id": 2,
            "name": "User 2",
            "scores": {
                "week": 60,
                "month": 80,
                "allTime": 95
            }
        },
        {
            "id": 3,
            "name": "User 3",
            "scores": {
                "week": 50,
                "month": 70,
                "allTime": 85
            }
        },
        {
            "id": 4,
            "name": "User 4",
            "scores": {
                "week": 79,
                "month": 20,
                "allTime": 60
            }
        },
        {
            "id": 5,
            "name": "User 5",
            "scores": {
                "week": 89,
                "month": 26,
                "allTime": 49
            }
        },
        {
            "id": 6,
            "name": "User 6",
            "scores": {
                "week": 63,
                "month": 45,
                "allTime": 36
            }
        },
        {
            "id": 7,
            "name": "User 7",
            "scores": {
                "week": 46,
                "month": 46,
                "allTime": 4
            }
        },
        {
            "id": 8,
            "name": "User 8",
            "scores": {
                "week": 28,
                "month": 18,
                "allTime": 32
            }
        },
        {
            "id": 9,
            "name": "User 9",
            "scores": {
                "week": 40,
                "month": 87,
                "allTime": 17
            }
        },
        {
            "id": 10,
            "name": "User 10",
            "scores": {
                "week": 16,
                "month": 25,
                "allTime": 84
            }
        },
        {
            "id": 11,
            "name": "User 11",
            "scores": {
                "week": 95,
                "month": 83,
                "allTime": 43
            }
        },
        {
            "id": 12,
            "name": "User 12",
            "scores": {
                "week": 16,
                "month": 100,
                "allTime": 31
            }
        },
        {
            "id": 13,
            "name": "User 13",
            "scores": {
                "week": 13,
                "month": 91,
                "allTime": 24
            }
        },
        {
            "id": 14,
            "name": "User 14",
            "scores": {
                "week": 56,
                "month": 97,
                "allTime": 42
            }
        },
        {
            "id": 15,
            "name": "User 15",
            "scores": {
                "week": 12,
                "month": 24,
                "allTime": 70
            }
        },
        {
            "id": 16,
            "name": "User 16",
            "scores": {
                "week": 88,
                "month": 92,
                "allTime": 19
            }
        },
        {
            "id": 17,
            "name": "User 17",
            "scores": {
                "week": 35,
                "month": 66,
                "allTime": 13
            }
        },
        {
            "id": 18,
            "name": "User 18",
            "scores": {
                "week": 36,
                "month": 70,
                "allTime": 88
            }
        },
        {
            "id": 19,
            "name": "User 19",
            "scores": {
                "week": 48,
                "month": 94,
                "allTime": 42
            }
        },
        {
            "id": 20,
            "name": "User 20",
            "scores": {
                "week": 17,
                "month": 65,
                "allTime": 99
            }
        },
        {
            "id": 21,
            "name": "User 21",
            "scores": {
                "week": 25,
                "month": 16,
                "allTime": 33
            }
        },
        {
            "id": 22,
            "name": "User 22",
            "scores": {
                "week": 34,
                "month": 49,
                "allTime": 16
            }
        },
        {
            "id": 23,
            "name": "User 23",
            "scores": {
                "week": 11,
                "month": 39,
                "allTime": 17
            }
        },
        {
            "id": 24,
            "name": "User 24",
            "scores": {
                "week": 91,
                "month": 12,
                "allTime": 88
            }
        },
        {
            "id": 25,
            "name": "User 25",
            "scores": {
                "week": 43,
                "month": 76,
                "allTime": 87
            }
        },
        {
            "id": 26,
            "name": "User 26",
            "scores": {
                "week": 70,
                "month": 82,
                "allTime": 46
            }
        },
        {
            "id": 27,
            "name": "User 27",
            "scores": {
                "week": 24,
                "month": 70,
                "allTime": 43
            }
        },
        {
            "id": 28,
            "name": "User 28",
            "scores": {
                "week": 21,
                "month": 82,
                "allTime": 25
            }
        },
        {
            "id": 29,
            "name": "User 29",
            "scores": {
                "week": 75,
                "month": 20,
                "allTime": 64
            }
        },
        {
            "id": 30,
            "name": "User 30",
            "scores": {
                "week": 61,
                "month": 0,
                "allTime": 57
            }
        },
        {
            "id": 31,
            "name": "User 31",
            "scores": {
                "week": 74,
                "month": 13,
                "allTime": 5
            }
        },
        {
            "id": 32,
            "name": "User 32",
            "scores": {
                "week": 40,
                "month": 84,
                "allTime": 59
            }
        },
        {
            "id": 33,
            "name": "User 33",
            "scores": {
                "week": 1,
                "month": 0,
                "allTime": 65
            }
        },
        {
            "id": 34,
            "name": "User 34",
            "scores": {
                "week": 77,
                "month": 71,
                "allTime": 74
            }
        },
        {
            "id": 35,
            "name": "User 35",
            "scores": {
                "week": 8,
                "month": 16,
                "allTime": 54
            }
        },
        {
            "id": 36,
            "name": "User 36",
            "scores": {
                "week": 69,
                "month": 80,
                "allTime": 85
            }
        },
        {
            "id": 37,
            "name": "User 37",
            "scores": {
                "week": 55,
                "month": 29,
                "allTime": 98
            }
        },
        {
            "id": 38,
            "name": "User 38",
            "scores": {
                "week": 80,
                "month": 89,
                "allTime": 16
            }
        },
        {
            "id": 39,
            "name": "User 39",
            "scores": {
                "week": 31,
                "month": 74,
                "allTime": 82
            }
        },
        {
            "id": 40,
            "name": "User 40",
            "scores": {
                "week": 79,
                "month": 45,
                "allTime": 14
            }
        },
        {
            "id": 41,
            "name": "User 41",
            "scores": {
                "week": 78,
                "month": 69,
                "allTime": 0
            }
        },
        {
            "id": 42,
            "name": "User 42",
            "scores": {
                "week": 1,
                "month": 3,
                "allTime": 60
            }
        },
        {
            "id": 43,
            "name": "User 43",
            "scores": {
                "week": 40,
                "month": 79,
                "allTime": 91
            }
        },
        {
            "id": 44,
            "name": "User 44",
            "scores": {
                "week": 39,
                "month": 87,
                "allTime": 21
            }
        },
        {
            "id": 45,
            "name": "User 45",
            "scores": {
                "week": 34,
                "month": 10,
                "allTime": 98
            }
        },
        {
            "id": 46,
            "name": "User 46",
            "scores": {
                "week": 77,
                "month": 56,
                "allTime": 100
            }
        },
        {
            "id": 47,
            "name": "User 47",
            "scores": {
                "week": 41,
                "month": 42,
                "allTime": 51
            }
        },
        {
            "id": 48,
            "name": "User 48",
            "scores": {
                "week": 76,
                "month": 38,
                "allTime": 87
            }
        },
        {
            "id": 49,
            "name": "User 49",
            "scores": {
                "week": 76,
                "month": 44,
                "allTime": 10
            }
        },
        {
            "id": 50,
            "name": "User 50",
            "scores": {
                "week": 34,
                "month": 75,
                "allTime": 72
            }
        }
    ]
}